tests/__init__.py
tests/test_config.py
tests/test_date_util.py
tests/test_json_parsers.py
tests/test_moratorios.py
tests/test_parcelas.py
tests/test_xml_parsers.py
tests/indices/__init__.py
tests/indices/test_indexador.py
tests/indices/test_indexador_banco_central.py
tests/indices/test_indexador_base.py
tests/indices/test_indexador_diario.py
tests/indices/test_indexador_mensal.py
tests/indices/test_indexador_secovi.py
tests/pos_fixado/__init__.py
tests/pos_fixado/test_calculo.py
tests/pos_fixado/test_fator_acumulado.py
violeta/__init__.py
violeta/calc.py
violeta/constantes.py
violeta/date_utils.py
violeta/fluxo_parcelas.py
violeta/pdd.py
violeta/utils.py
violeta/config/__init__.py
violeta/config/config.ini
violeta/data/ANBIMA.txt
violeta/docs/__init__.py
violeta/exceptions/__init__.py
violeta/indices/__init__.py
violeta/indices/cdi.py
violeta/indices/igpm.py
violeta/indices/incc.py
violeta/indices/indexador.py
violeta/indices/indexador_banco_central.py
violeta/indices/indexador_base.py
violeta/indices/indexador_diario.py
violeta/indices/indexador_mensal.py
violeta/indices/indexador_secovi.py
violeta/indices/ipca.py
violeta/parsers/__init__.py
violeta/parsers/base.py
violeta/parsers/json_parser.py
violeta/parsers/xml_parser.py
violeta/pos_fixado/__init__.py
violeta/pos_fixado/calculo.py
violeta/pos_fixado/fator_acumulado.py
violeta/pos_fixado/models/__init__.py
violeta/pos_fixado/models/contrato.py
violeta/pos_fixado/models/pagamento.py
violeta/pos_fixado/models/parcela.py
violeta/pos_fixado/models/valores_atraso.py
violeta_master-0.0.1.dist-info/LICENSE
violeta_master-0.0.1.dist-info/METADATA
violeta_master-0.0.1.dist-info/WHEEL
violeta_master-0.0.1.dist-info/top_level.txt
violeta_master-0.0.1.dist-info/RECORD
